easy_caesar/__init__.py
easy_caesar/cipher.py
easy_caesar/example.py
easy_caesar/bin/__init__.py
easy_caesar/bin/script.py
easy_caesar-0.1.0.dist-info/LICENSE
easy_caesar-0.1.0.dist-info/METADATA
easy_caesar-0.1.0.dist-info/WHEEL
easy_caesar-0.1.0.dist-info/entry_points.txt
easy_caesar-0.1.0.dist-info/top_level.txt
easy_caesar-0.1.0.dist-info/RECORD
